api_routes.py
kgit.py
kospex.py
kospex_agent.py
kospex_bitbucket.py
kospex_core.py
kospex_dependencies.py
kospex_email.py
kospex_git.py
kospex_github.py
kospex_logging.py
kospex_mergestat.py
kospex_observation.py
kospex_query.py
kospex_request_cache.py
kospex_schema.py
kospex_stats.py
kospex_utils.py
kospex_web.py
kreaper.py
krunner.py
krunner_utils.py
kweb2.py
kweb_graph_service.py
kweb_help_service.py
kweb_security.py
repo_sync.py
yearly.py
yearly_repos.py
kospex-0.0.32.dist-info/licenses/LICENSE
static/css/datatables.min.css
static/css/input.css
static/css/tailwind.css
static/js/chart.min.js
static/js/d3.min.js
static/js/datatables.min.js
static/js/jquery.min.js
templates/404.html
templates/_datatable_scripts.html
templates/_footer_scripts.html
templates/_header.html
templates/_id_header_macro.html
templates/_radar_macro.html
templates/_single_radar.html
templates/bubble.html
templates/collab.html
templates/collab_graph.html
templates/commit.html
templates/commits.html
templates/dependencies.html
templates/developer_view.html
templates/developers.html
templates/file_collaboration.html
templates/files.html
templates/graph.html
templates/header.html
templates/hotspots.html
templates/key_person.html
templates/landscape.html
templates/meta-author-domains.html
templates/metadata.html
templates/metadata_repos.html
templates/observation.html
templates/observations.html
templates/observations_repo.html
templates/observations_repo_key.html
templates/orgs.html
templates/orphans.html
templates/osi.html
templates/package_check.html
templates/recent-syncs.html
templates/repo_files.html
templates/repo_view.html
templates/repos-tech.html
templates/repos.html
templates/servers.html
templates/summary.html
templates/summary2.html
templates/summary_4col.html
templates/supply_chain.html
templates/supply_chain_search.html
templates/tech-change.html
templates/tenure.html
templates/treemap.html
templates/help/index.html
kospex-0.0.32.dist-info/METADATA
kospex-0.0.32.dist-info/WHEEL
kospex-0.0.32.dist-info/entry_points.txt
kospex-0.0.32.dist-info/top_level.txt
kospex-0.0.32.dist-info/RECORD
