Metadata-Version: 2.4
Name: kospex
Version: 0.0.32
Summary: kospex - Code and Developer Analytics.
Author-email: Peter Freiberg <peter.freiberg@gmail.com>
License: MIT License
Project-URL: Homepage, https://kospex.io
Project-URL: Issues, https://github.com/kospex/kospex/issues
Project-URL: Repository, https://github.com/kospex/kospex
Keywords: analytics,git,code analytics,developer analytics,open source inventory,predictive maintenance
Classifier: Programming Language :: Python :: 3
Requires-Python: >=3.11
License-File: LICENSE
Requires-Dist: Click
Requires-Dist: flask
Requires-Dist: prettytable
Requires-Dist: dateutils
Requires-Dist: panopticas>=0.0.13
Requires-Dist: python-dotenv
Requires-Dist: sqlite_utils
Requires-Dist: requests
Requires-Dist: rich>=14.0.0
Requires-Dist: PyGithub==2.6.1
Requires-Dist: python-multipart>=0.0.20
Requires-Dist: PyYAML
Requires-Dist: mkdocs
Requires-Dist: jinja2>=3.1.6
Requires-Dist: fastapi>=0.116.0
Requires-Dist: uvicorn>=0.35.0
Dynamic: license-file
